{"USD":{"success":true,"timestamp":1736184724,"base":"USD","date":"2025-01-06","rates":{"EUR":0.963265,"PLN":4.097095,"BYN":3.275708}},"PLN":{"success":true,"timestamp":1736184724,"base":"PLN","date":"2025-01-06","rates":{"EUR":0.235109,"USD":0.244075,"BYN":0.79952}},"BYN":{"success":true,"timestamp":1736184724,"base":"BYN","date":"2025-01-06","rates":{"EUR":0.294063,"USD":0.305278,"PLN":1.250751}},"EUR":{"success":true,"timestamp":1736184724,"base":"EUR","date":"2025-01-06","rates":{"USD":1.038136,"PLN":4.253342,"BYN":3.40063}}}